brainrevenge/__init__.py
brainrevenge/_version.py
brainrevenge-0.0.0.dist-info/AUTHORS.rst
brainrevenge-0.0.0.dist-info/LICENSE.md
brainrevenge-0.0.0.dist-info/METADATA
brainrevenge-0.0.0.dist-info/WHEEL
brainrevenge-0.0.0.dist-info/top_level.txt
brainrevenge-0.0.0.dist-info/RECORD
