Metadata-Version: 2.1
Name: brainrevenge
Version: 0.0.0
Summary: BrainRevenge Project Library
Home-page: https://brainrevenge.github.io/brainrevenge/
Author: Fede Raimondo
Author-email: f.raimondo@fz-juelich.de
License: UNKNOWN
Download-URL: https://github.com/brainrevenge/brainrevenge
Project-URL: Documentation, https://brainrevenge.github.io/brainrevenge/
Project-URL: Source, https://github.com/brainrevenge/brainrevenge
Project-URL: Tracker, https://github.com/brainrevenge/brainrevengeissues/
Platform: UNKNOWN
Classifier: Intended Audience :: Science/Research
Classifier: Intended Audience :: Developers
Classifier: License :: OSI Approved
Classifier: Programming Language :: Python
Classifier: Topic :: Software Development
Classifier: Topic :: Scientific/Engineering
Classifier: Operating System :: Microsoft :: Windows
Classifier: Operating System :: POSIX
Classifier: Operating System :: Unix
Classifier: Operating System :: MacOS
Classifier: Programming Language :: Python :: 3
Requires-Python: >=3.6
